abdbeam/__init__.py
abdbeam/core.py
abdbeam/materials.py
abdbeam/plots.py
abdbeam/examples/__init__.py
abdbeam/examples/example_bruhn.py
abdbeam/examples/example_hat.py
abdbeam/examples/example_kollar_springer_open.py
abdbeam/examples/example_kollar_springer_single_cell.py
abdbeam/examples/example_megson.py
abdbeam/examples/example_torque_box.py
abdbeam/examples/example_victorazzo.py
abdbeam-0.2.1.dist-info/LICENSE
abdbeam-0.2.1.dist-info/METADATA
abdbeam-0.2.1.dist-info/WHEEL
abdbeam-0.2.1.dist-info/top_level.txt
abdbeam-0.2.1.dist-info/RECORD
