Metadata-Version: 2.1
Name: abdbeam
Version: 0.2.1
Summary: Cross section analysis of composite material beams of any shape.
Home-page: https://github.com/victorazzo/abdbeam
Author: Danilo S. Victorazzo
Author-email: victorazzo@gmail.com
License: BSD-3
Platform: UNKNOWN
Classifier: Natural Language :: English
Classifier: Intended Audience :: Science/Research
Classifier: Programming Language :: Python :: 3.6
Classifier: Programming Language :: Python :: 3.7
Classifier: License :: OSI Approved :: BSD License
Classifier: Topic :: Scientific/Engineering
Classifier: Operating System :: OS Independent
